flask_uwsgi_ws/__init__.py
flask_uwsgi_ws/__version__.py
flask_uwsgi_ws/_async.py
flask_uwsgi_ws/_asyncio.py
flask_uwsgi_ws/_gevent.py
flask_uwsgi_ws/_uwsgi.py
flask_uwsgi_ws/websocket.py
flask_uwsgi_ws-0.4.0.dist-info/LICENSE
flask_uwsgi_ws-0.4.0.dist-info/WHEEL
flask_uwsgi_ws-0.4.0.dist-info/METADATA
flask_uwsgi_ws-0.4.0.dist-info/RECORD
